{
    "version": "2.0.16",
    "architecture": {
        "64bit": {
            "url": "https://storage.googleapis.com/thunder-cli/tnr/releases/2.0.16/windows/tnr_2.0.16_windows_amd64.zip",
            "bin": [
                "tnr.exe"
            ],
            "hash": "0b638a031d9a35167f279b797085adc4bc021adee111941a4cdd2f8ab296cd17"
        },
        "arm64": {
            "url": "https://storage.googleapis.com/thunder-cli/tnr/releases/2.0.16/windows/tnr_2.0.16_windows_arm64.zip",
            "bin": [
                "tnr.exe"
            ],
            "hash": "9c87c7f35a53b01ebd1f80dafa715513e80ad52ead1d7603139f03134dcec7ac"
        }
    },
    "homepage": "https://github.com/Thunder-Compute/thunder-cli",
    "license": "MIT",
    "description": "Thunder Compute CLI"
}
